kasal/__init__.py
kasal/app/__init__.py
kasal/app/polyscope_app.py
kasal/bop_toolkit_lib/__init__.py
kasal/bop_toolkit_lib/inout.py
kasal/bop_toolkit_lib/misc.py
kasal/bop_toolkit_lib/transform.py
kasal/bop_toolkit_lib/view_sampler.py
kasal/config/__init__.py
kasal/config/config.py
kasal/datasets/K10.png
kasal/datasets/K11.png
kasal/datasets/K12.png
kasal/datasets/K13.png
kasal/datasets/K14.png
kasal/datasets/K15.png
kasal/datasets/K16.png
kasal/datasets/K4.ico
kasal/datasets/K8.ico
kasal/datasets/K9.png
kasal/datasets/__init__.py
kasal/datasets/arrow.ply
kasal/datasets/arrow_xyz.ply
kasal/datasets/datasets_path.py
kasal/datasets/fig1.png
kasal/datasets/icon_md.png
kasal/datasets/result-p20-1.png
kasal/datasets/result-p20-2.png
kasal/datasets/show xyz.png
kasal/datasets/__pycache__/__init__.cpython-39.pyc
kasal/datasets/__pycache__/datasets_path.cpython-39.pyc
kasal/datasets/shape_meshes/KASAL.json
kasal/datasets/shape_meshes/obj_000007.STEP
kasal/datasets/shape_meshes/obj_000007.STL
kasal/datasets/shape_meshes/obj_000007_ours.ply
kasal/datasets/shape_meshes/obj_000007_ours_sym.ply
kasal/datasets/shape_meshes/obj_000007_ours_sym_type.json
kasal/datasets/shape_meshes/obj_000008.STEP
kasal/datasets/shape_meshes/obj_000008.STL
kasal/datasets/shape_meshes/obj_000008_ours.ply
kasal/datasets/shape_meshes/obj_000008_ours_sym.ply
kasal/datasets/shape_meshes/obj_000008_ours_sym_type.json
kasal/datasets/texture_meshes/KASAL.json
kasal/datasets/texture_meshes/obj_000001_t.jpg
kasal/datasets/texture_meshes/obj_000001_t.mtl
kasal/datasets/texture_meshes/obj_000001_t.obj
kasal/datasets/texture_meshes/obj_000001_t_sym.ply
kasal/datasets/texture_meshes/obj_000001_t_sym_type.json
kasal/geometry/__init__.py
kasal/geometry/circular_sampling.py
kasal/geometry/o3d_icp.py
kasal/keyaxis/__init__.py
kasal/keyaxis/color_error.py
kasal/keyaxis/keyaxis.py
kasal/keyaxis/rotate.py
kasal/symmetry_lab/__init__.py
kasal/symmetry_lab/symmetry_axis_localization.py
kasal_python-0.1.0.dist-info/licenses/LICENSE.txt
kasal_python-0.1.0.dist-info/METADATA
kasal_python-0.1.0.dist-info/WHEEL
kasal_python-0.1.0.dist-info/top_level.txt
kasal_python-0.1.0.dist-info/RECORD
