Metadata-Version: 2.4
Name: kasal-python
Version: 0.1.0
Summary: kasal is a project designed for determining the symmetry axis orientation and the rotation center of rotationally symmetric objects.
Author-email: Yulin Wang <yulinwang@seu.edu.cn>, Mengting Hu <220240361@seu.edu.cn>
Maintainer-email: Yulin Wang <yulinwang@seu.edu.cn>, Mengting Hu <220240361@seu.edu.cn>
License-Expression: Apache-2.0
Project-URL: Homepage, https://github.com/WangYuLin-SEU/KASAL
License-File: LICENSE.txt
Requires-Dist: imageio
Requires-Dist: pypng
Requires-Dist: pytz
Requires-Dist: open3d
Requires-Dist: tqdm
Requires-Dist: chardet
Requires-Dist: trimesh
Requires-Dist: pywin32
Requires-Dist: fpsample==0.3.1
Requires-Dist: polyscope==2.3.0
Requires-Dist: numpy==1.25.2
Requires-Dist: opencv-python==4.5.5.64
Requires-Dist: opencv-contrib-python==4.5.5.64
Requires-Dist: pymeshlab==2023.12.post1
Requires-Dist: scipy==1.10.1
Dynamic: license-file
